rinopy/__init__.py
rinopy/ml/__init__.py
rinopy/ml/model_evaluations/__init__.py
rinopy/ml/model_evaluations/eval.py
rinopy-0.0.2.dist-info/METADATA
rinopy-0.0.2.dist-info/WHEEL
rinopy-0.0.2.dist-info/top_level.txt
rinopy-0.0.2.dist-info/RECORD
